nanoplm/__init__.py
nanoplm/cli/__init__.py
nanoplm/cli/data.py
nanoplm/cli/distill.py
nanoplm/cli/pretrain.py
nanoplm/config/__init__.py
nanoplm/config/datasets.py
nanoplm/data/__init__.py
nanoplm/data/dataset.py
nanoplm/data/downloader.py
nanoplm/data/extractor.py
nanoplm/data/filterer.py
nanoplm/data/shuffler.py
nanoplm/data/splitor.py
nanoplm/distillation/__init__.py
nanoplm/distillation/collator.py
nanoplm/distillation/pipeline.py
nanoplm/distillation/pipeline_builder.py
nanoplm/distillation/session_manager.py
nanoplm/distillation/trainer.py
nanoplm/models/__init__.py
nanoplm/models/student/__init__.py
nanoplm/models/student/feature_embedding.py
nanoplm/models/student/model.py
nanoplm/models/student/pca.csv
nanoplm/models/student/tokenizer.py
nanoplm/models/teacher/__init__.py
nanoplm/models/teacher/base.py
nanoplm/models/teacher/prott5.py
nanoplm/pretraining/__init__.py
nanoplm/pretraining/collator.py
nanoplm/pretraining/dataset.py
nanoplm/pretraining/pipeline.py
nanoplm/pretraining/models/__init__.py
nanoplm/pretraining/models/modern_bert/__init__.py
nanoplm/pretraining/models/modern_bert/model.py
nanoplm/pretraining/models/modern_bert/tokenizer.py
nanoplm/utils/__init__.py
nanoplm/utils/common.py
nanoplm/utils/logger.py
nanoplm-0.1.6.dist-info/licenses/LICENSE
nanoplm-0.1.6.dist-info/METADATA
nanoplm-0.1.6.dist-info/WHEEL
nanoplm-0.1.6.dist-info/entry_points.txt
nanoplm-0.1.6.dist-info/top_level.txt
nanoplm-0.1.6.dist-info/RECORD
