Metadata-Version: 2.4
Name: nanoplm
Version: 0.1.6
Summary: Make your own protein language model, faster than ever.
Author-email: Peyman Vahidi <peyman.vahidi@helmholtz-munich.de>
License: MIT
Project-URL: Homepage, https://github.com/peymanvahidi/nanoplm
Keywords: bioinformatics,protein-language-model,large-language-models
Classifier: Development Status :: 3 - Alpha
Classifier: Intended Audience :: Developers
Classifier: Intended Audience :: Science/Research
Classifier: License :: OSI Approved :: MIT License
Classifier: Operating System :: OS Independent
Classifier: Programming Language :: Python
Classifier: Natural Language :: English
Classifier: Topic :: Scientific/Engineering :: Bio-Informatics
Classifier: Programming Language :: Python
Classifier: Programming Language :: Python :: 3
Classifier: Programming Language :: Python :: 3.10
Classifier: Programming Language :: Python :: 3.11
Classifier: Programming Language :: Python :: 3.12
Requires-Python: >=3.10
License-File: LICENSE
Requires-Dist: accelerate>=1.7.0
Requires-Dist: biopython>=1.85
Requires-Dist: click>=8.1.8
Requires-Dist: dvc>=3.59.1
Requires-Dist: h5py>=3.13.0
Requires-Dist: pyyaml>=6.0.2
Requires-Dist: safetensors>=0.4.0
Requires-Dist: seaborn>=0.13.2
Requires-Dist: sentencepiece>=0.2.0
Requires-Dist: torch>=2.5.4
Requires-Dist: tqdm>=4.67.1
Requires-Dist: transformers>=4.50.2
Requires-Dist: wandb>=0.19.11
Requires-Dist: certifi>=2024.7.4
Requires-Dist: ipython>=8.3.0
Dynamic: license-file
